{
  "namespace": "OrangoDemoTools",
  "fsNamespace": "orango-demo-tools",
  "loader": "../orango-demo-tools.js",
  "core": "orango-demo-tools.n0mre3jk.js",
  "corePolyfilled": "orango-demo-tools.w8adkvqk.js",
  "components": {
    "o-demo-bar": {
      "bundleIds": {
        "$": "vwwpauft"
      },
      "encapsulation": "shadow"
    },
    "o-demo-bar-buttons": {
      "bundleIds": {
        "$": "vwwpauft"
      },
      "encapsulation": "shadow"
    },
    "o-demo-bar-select": {
      "bundleIds": {
        "$": "vwwpauft"
      },
      "encapsulation": "shadow"
    },
    "o-demo-bar-toolbar": {
      "bundleIds": {
        "$": "vwwpauft"
      },
      "encapsulation": "shadow"
    },
    "o-demo-case": {
      "bundleIds": {
        "$": "gwhkzfcf"
      },
      "encapsulation": "shadow"
    },
    "o-demo-devices": {
      "bundleIds": {
        "$": "vwwpauft"
      },
      "encapsulation": "shadow"
    },
    "o-demo-fab": {
      "bundleIds": {
        "$": "vwwpauft"
      },
      "encapsulation": "shadow"
    },
    "o-demo-modal": {
      "bundleIds": {
        "$": "mhek6vzf"
      },
      "encapsulation": "shadow"
    },
    "o-demo-resizer": {
      "bundleIds": {
        "$": "vwwpauft"
      },
      "encapsulation": "shadow"
    },
    "o-demo-snackbar": {
      "bundleIds": {
        "$": "vwwpauft"
      },
      "encapsulation": "shadow"
    }
  }
}